Workbook

Sheet Resumo
B2: ROI Seeding 2025/2026
B3: Free sample REAL da API (sample_applications) · peça enviada = COMPLETED/SHIPPED/CONTENT_PENDING · GMV = afiliação da creator (Affiliate Orders) na janela do convite · coorte por MÊS do convite
B5: Premissas (edite os valores em amarelo — tudo recalcula)
B6: Custo unitário da peça-amostra (COGS) | C6: 40 | D6: ← custo de produção de 1 peça
B7: Frete por envio (por creator) | C7: 25 | D7: ← logística de 1 remessa
B8: Margem de contribuição sobre GMV | C8: 0.55 | D8: ← quanto do GMV vira lucro antes de comissão/seeding
B10: Resultado consolidado
B11: Creators que receberam amostra | C11: 113
B12: Peças enviadas (total) | C12: =SUM('ROI por creator'!I2:I273)
B13: Peças pedidas (inclui canceladas) | C13: =SUM('ROI por creator'!H2:H273)
B14: Peças canceladas (não enviadas) | C14: =SUM('ROI por creator'!J2:J273)
B15: GMV atribuído (afiliação pós-convite) | C15: =SUM('ROI por creator'!Q2:Q273)
B16: Comissão paga sobre seeding | C16: =SUM('ROI por creator'!R2:R273)
B17: Custo total de seeding (peças+frete) | C17: =SUM('ROI por creator'!O2:O273)
B18: Margem de contribuição gerada | C18: =SUM('ROI por creator'!S2:S273)
B19: Lucro líquido do seeding | C19: =SUM('ROI por creator'!T2:T273)
B20: ROAS (GMV ÷ custo seeding) | C20: =IF(SUM('ROI por creator'!O2:O273)>0,SUM('ROI por creator'!Q2:Q273)/SUM('ROI por creator'!O2:O273),0)
B21: ROI (lucro ÷ custo seeding) | C21: =IF(SUM('ROI por creator'!O2:O273)>0,SUM('ROI por creator'!T2:T273)/SUM('ROI por creator'!O2:O273),0)
B22: Custo por peça enviada | C22: =IF(SUM('ROI por creator'!I2:I273)>0,SUM('ROI por creator'!O2:O273)/SUM('ROI por creator'!I2:I273),0)

Sheet ROI por creator
A1: # | B1: Creator | C1: @ TikTok | D1: Status envio | E1: Mês convite | F1: 1º convite | G1: Último convite | H1: Peças pedidas | I1: Peças enviadas | J1: Peças canceladas | K1: SKUs amostrados | L1: Comissão % | M1: Custo amostra (R$) | N1: Frete (R$) | O1: Custo seeding (R$) | P1: Pedidos atrib. | Q1: GMV atribuído (R$) | R1: Comissão paga (R$) | S1: Margem contrib. (R$) | T1: Lucro líquido (R$) | U1: ROAS | V1: ROI
A2: 1 | B2: Flávia Cunha | C2: @flavia.cunha__ | D2: Enviado | E2: 2025-06 | F2: 2025-06-27 | G2: 2025-06-27 | H2: 2 | I2: 2 | J2: 0 | K2: 2 | L2: 0.08 | M2: =I2*Resumo!$C$6 | N2: =IF(I2>0,Resumo!$C$7,0) | O2: =M2+N2 | P2: 1 | Q2: 79.9 | R2: 7.99 | S2: =Q2*Resumo!$C$8 | T2: =S2-R2-O2 | U2: =IF(O2>0,Q2/O2,0) | V2: =IF(O2>0,T2/O2,0)
A3: 2 | B3: TATÁ 🎀 | C3: @luccianagomees | D3: Enviado | E3: 2025-06 | F3: 2025-06-27 | G3: 2025-06-27 | H3: 1 | I3: 1 | J3: 0 | K3: 1 | L3: 0.08 | M3: =I3*Resumo!$C$6 | N3: =IF(I3>0,Resumo!$C$7,0) | O3: =M3+N3 | P3: 0 | Q3: 0 | R3: 0 | S3: =Q3*Resumo!$C$8 | T3: =S3-R3-O3 | U3: =IF(O3>0,Q3/O3,0) | V3: =IF(O3>0,T3/O3,0)
A4: 3 | B4: Yasmin Oliveira | C4: @yasmin.aoliveira | D4: Enviado | E4: 2025-06 | F4: 2025-06-27 | G4: 2025-06-27 | H4: 1 | I4: 1 | J4: 0 | K4: 1 | L4: 0.08 | M4: =I4*Resumo!$C$6 | N4: =IF(I4>0,Resumo!$C$7,0) | O4: =M4+N4 | P4: 0 | Q4: 0 | R4: 0 | S4: =Q4*Resumo!$C$8 | T4: =S4-R4-O4 | U4: =IF(O4>0,Q4/O4,0) | V4: =IF(O4>0,T4/O4,0)
A5: 4 | B5: numarchi | C5: @numarchi | D5: Enviado | E5: 2025-06 | F5: 2025-06-28 | G5: 2025-06-28 | H5: 1 | I5: 1 | J5: 0 | K5: 1 | L5: 0.12 | M5: =I5*Resumo!$C$6 | N5: =IF(I5>0,Resumo!$C$7,0) | O5: =M5+N5 | P5: 0 | Q5: 0 | R5: 0 | S5: =Q5*Resumo!$C$8 | T5: =S5-R5-O5 | U5: =IF(O5>0,Q5/O5,0) | V5: =IF(O5>0,T5/O5,0)
A6: 5 | B6: Laiane Novais | C6: @laianenovaisss | D6: Enviado | E6: 2025-06 | F6: 2025-06-30 | G6: 2025-06-30 | H6: 2 | I6: 2 | J6: 0 | K6: 2 | L6: 0.12 | M6: =I6*Resumo!$C$6 | N6: =IF(I6>0,Resumo!$C$7,0) | O6: =M6+N6 | P6: 0 | Q6: 0 | R6: 0 | S6: =Q6*Resumo!$C$8 | T6: =S6-R6-O6 | U6: =IF(O6>0,Q6/O6,0) | V6: =IF(O6>0,T6/O6,0)
A7: 6 | B7: Maria Augusta Reis | C7: @mariaaugustareiss | D7: Enviado | E7: 2025-06 | F7: 2025-06-30 | G7: 2025-06-30 | H7: 2 | I7: 2 | J7: 0 | K7: 2 | L7: 0.08 | M7: =I7*Resumo!$C$6 | N7: =IF(I7>0,Resumo!$C$7,0) | O7: =M7+N7 | P7: 0 | Q7: 0 | R7: 0 | S7: =Q7*Resumo!$C$8 | T7: =S7-R7-O7 | U7: =IF(O7>0,Q7/O7,0) | V7: =IF(O7>0,T7/O7,0)
A8: 7 | B8: Laiane Novais | C8: @laianenovaisss | D8: Enviado | E8: 2025-07 | F8: 2025-07-16 | G8: 2025-07-16 | H8: 1 | I8: 1 | J8: 0 | K8: 1 | L8: 0.12 | M8: =I8*Resumo!$C$6 | N8: =IF(I8>0,Resumo!$C$7,0) | O8: =M8+N8 | P8: 0 | Q8: 0 | R8: 0 | S8: =Q8*Resumo!$C$8 | T8: =S8-R8-O8 | U8: =IF(O8>0,Q8/O8,0) | V8: =IF(O8>0,T8/O8,0)
A9: 8 | B9: Maria Augusta Reis | C9: @mariaaugustareiss | D9: Enviado | E9: 2025-07 | F9: 2025-07-18 | G9: 2025-07-18 | H9: 1 | I9: 1 | J9: 0 | K9: 1 | L9: 0.08 | M9: =I9*Resumo!$C$6 | N9: =IF(I9>0,Resumo!$C$7,0) | O9: =M9+N9 | P9: 51 | Q9: 4318.54 | R9: 370.11 | S9: =Q9*Resumo!$C$8 | T9: =S9-R9-O9 | U9: =IF(O9>0,Q9/O9,0) | V9: =IF(O9>0,T9/O9,0)
A10: 9 | B10: Yasmin Oliveira | C10: @yasmin.aoliveira | D10: Enviado | E10: 2025-07 | F10: 2025-07-18 | G10: 2025-07-18 | H10: 1 | I10: 1 | J10: 0 | K10: 1 | L10: 0.08 | M10: =I10*Resumo!$C$6 | N10: =IF(I10>0,Resumo!$C$7,0) | O10: =M10+N10 | P10: 0 | Q10: 0 | R10: 0 | S10: =Q10*Resumo!$C$8 | T10: =S10-R10-O10 | U10: =IF(O10>0,Q10/O10,0) | V10: =IF(O10>0,T10/O10,0)
A11: 10 | B11: numarchi | C11: @numarchi | D11: Enviado | E11: 2025-07 | F11: 2025-07-21 | G11: 2025-07-21 | H11: 1 | I11: 1 | J11: 0 | K11: 1 | L11: 0.12 | M11: =I11*Resumo!$C$6 | N11: =IF(I11>0,Resumo!$C$7,0) | O11: =M11+N11 | P11: 0 | Q11: 0 | R11: 0 | S11: =Q11*Resumo!$C$8 | T11: =S11-R11-O11 | U11: =IF(O11>0,Q11/O11,0) | V11: =IF(O11>0,T11/O11,0)
A12: 11 | B12: Roberta Frias | C12: @robertafrias | D12: Enviado | E12: 2025-08 | F12: 2025-08-09 | G12: 2025-08-09 | H12: 1 | I12: 1 | J12: 0 | K12: 1 | L12: 0.08 | M12: =I12*Resumo!$C$6 | N12: =IF(I12>0,Resumo!$C$7,0) | O12: =M12+N12 | P12: 1 | Q12: 79.9 | R12: 7.99 | S12: =Q12*Resumo!$C$8 | T12: =S12-R12-O12 | U12: =IF(O12>0,Q12/O12,0) | V12: =IF(O12>0,T12/O12,0)
A13: 12 | B13: Patty Lazzarotto | C13: @pattylazzarotto | D13: Enviado | E13: 2025-08 | F13: 2025-08-12 | G13: 2025-08-12 | H13: 1 | I13: 1 | J13: 0 | K13: 1 | L13: 0.12 | M13: =I13*Resumo!$C$6 | N13: =IF(I13>0,Resumo!$C$7,0) | O13: =M13+N13 | P13: 188 | Q13: 15615.74 | R13: 617.31 | S13: =Q13*Resumo!$C$8 | T13: =S13-R13-O13 | U13: =IF(O13>0,Q13/O13,0) | V13: =IF(O13>0,T13/O13,0)
... A273: 272 | B273: Welina | C273: @welinashop | D273: Nada enviado | E273: — | F273: — | G273: — | H273: 1 | I273: 0 | J273: 1 | K273: 1 | L273: 0.08 | M273: =I273*Resumo!$C$6 | N273: =IF(I273>0,Resumo!$C$7,0) | O273: =M273+N273 | P273: 0 | Q273: 0 | R273: 0 | S273: =Q273*Resumo!$C$8 | T273: =S273-R273-O273 | U273: =IF(O273>0,Q273/O273,0) | V273: =IF(O273>0,T273/O273,0)
D274: TOTAL (filtrado) | H274: =SUBTOTAL(109,H2:H273) | I274: =SUBTOTAL(109,I2:I273) | J274: =SUBTOTAL(109,J2:J273) | O274: =SUBTOTAL(109,O2:O273) | P274: =SUBTOTAL(109,P2:P273) | Q274: =SUBTOTAL(109,Q2:Q273) | R274: =SUBTOTAL(109,R2:R273) | S274: =SUBTOTAL(109,S2:S273) | T274: =SUBTOTAL(109,T2:T273) | U274: =IF(O274>0,Q274/O274,0) | V274: =IF(O274>0,T274/O274,0)

Sheet Resumo por mês
A1: Mês | B1: Creators (convites) | C1: Peças enviadas | D1: Peças canceladas | E1: Custo seeding (R$) | F1: GMV atribuído (R$) | G1: Comissão paga (R$) | H1: Lucro líquido (R$) | I1: ROAS | J1: ROI
A2: 2025-06 | B2: =COUNTIF('ROI por creator'!E2:E273,$A2) | C2: =SUMIF('ROI por creator'!E2:E273,$A2,'ROI por creator'!I2:I273) | D2: =SUMIF('ROI por creator'!E2:E273,$A2,'ROI por creator'!J2:J273) | E2: =SUMIF('ROI por creator'!E2:E273,$A2,'ROI por creator'!O2:O273) | F2: =SUMIF('ROI por creator'!E2:E273,$A2,'ROI por creator'!Q2:Q273) | G2: =SUMIF('ROI por creator'!E2:E273,$A2,'ROI por creator'!R2:R273) | H2: =SUMIF('ROI por creator'!E2:E273,$A2,'ROI por creator'!T2:T273) | I2: =IF(E2>0,F2/E2,0) | J2: =IF(E2>0,H2/E2,0)
A3: 2025-07 | B3: =COUNTIF('ROI por creator'!E2:E273,$A3) | C3: =SUMIF('ROI por creator'!E2:E273,$A3,'ROI por creator'!I2:I273) | D3: =SUMIF('ROI por creator'!E2:E273,$A3,'ROI por creator'!J2:J273) | E3: =SUMIF('ROI por creator'!E2:E273,$A3,'ROI por creator'!O2:O273) | F3: =SUMIF('ROI por creator'!E2:E273,$A3,'ROI por creator'!Q2:Q273) | G3: =SUMIF('ROI por creator'!E2:E273,$A3,'ROI por creator'!R2:R273) | H3: =SUMIF('ROI por creator'!E2:E273,$A3,'ROI por creator'!T2:T273) | I3: =IF(E3>0,F3/E3,0) | J3: =IF(E3>0,H3/E3,0)
A4: 2025-08 | B4: =COUNTIF('ROI por creator'!E2:E273,$A4) | C4: =SUMIF('ROI por creator'!E2:E273,$A4,'ROI por creator'!I2:I273) | D4: =SUMIF('ROI por creator'!E2:E273,$A4,'ROI por creator'!J2:J273) | E4: =SUMIF('ROI por creator'!E2:E273,$A4,'ROI por creator'!O2:O273) | F4: =SUMIF('ROI por creator'!E2:E273,$A4,'ROI por creator'!Q2:Q273) | G4: =SUMIF('ROI por creator'!E2:E273,$A4,'ROI por creator'!R2:R273) | H4: =SUMIF('ROI por creator'!E2:E273,$A4,'ROI por creator'!T2:T273) | I4: =IF(E4>0,F4/E4,0) | J4: =IF(E4>0,H4/E4,0)
A5: 2025-09 | B5: =COUNTIF('ROI por creator'!E2:E273,$A5) | C5: =SUMIF('ROI por creator'!E2:E273,$A5,'ROI por creator'!I2:I273) | D5: =SUMIF('ROI por creator'!E2:E273,$A5,'ROI por creator'!J2:J273) | E5: =SUMIF('ROI por creator'!E2:E273,$A5,'ROI por creator'!O2:O273) | F5: =SUMIF('ROI por creator'!E2:E273,$A5,'ROI por creator'!Q2:Q273) | G5: =SUMIF('ROI por creator'!E2:E273,$A5,'ROI por creator'!R2:R273) | H5: =SUMIF('ROI por creator'!E2:E273,$A5,'ROI por creator'!T2:T273) | I5: =IF(E5>0,F5/E5,0) | J5: =IF(E5>0,H5/E5,0)
A6: 2025-10 | B6: =COUNTIF('ROI por creator'!E2:E273,$A6) | C6: =SUMIF('ROI por creator'!E2:E273,$A6,'ROI por creator'!I2:I273) | D6: =SUMIF('ROI por creator'!E2:E273,$A6,'ROI por creator'!J2:J273) | E6: =SUMIF('ROI por creator'!E2:E273,$A6,'ROI por creator'!O2:O273) | F6: =SUMIF('ROI por creator'!E2:E273,$A6,'ROI por creator'!Q2:Q273) | G6: =SUMIF('ROI por creator'!E2:E273,$A6,'ROI por creator'!R2:R273) | H6: =SUMIF('ROI por creator'!E2:E273,$A6,'ROI por creator'!T2:T273) | I6: =IF(E6>0,F6/E6,0) | J6: =IF(E6>0,H6/E6,0)
A7: 2025-11 | B7: =COUNTIF('ROI por creator'!E2:E273,$A7) | C7: =SUMIF('ROI por creator'!E2:E273,$A7,'ROI por creator'!I2:I273) | D7: =SUMIF('ROI por creator'!E2:E273,$A7,'ROI por creator'!J2:J273) | E7: =SUMIF('ROI por creator'!E2:E273,$A7,'ROI por creator'!O2:O273) | F7: =SUMIF('ROI por creator'!E2:E273,$A7,'ROI por creator'!Q2:Q273) | G7: =SUMIF('ROI por creator'!E2:E273,$A7,'ROI por creator'!R2:R273) | H7: =SUMIF('ROI por creator'!E2:E273,$A7,'ROI por creator'!T2:T273) | I7: =IF(E7>0,F7/E7,0) | J7: =IF(E7>0,H7/E7,0)
A8: 2025-12 | B8: =COUNTIF('ROI por creator'!E2:E273,$A8) | C8: =SUMIF('ROI por creator'!E2:E273,$A8,'ROI por creator'!I2:I273) | D8: =SUMIF('ROI por creator'!E2:E273,$A8,'ROI por creator'!J2:J273) | E8: =SUMIF('ROI por creator'!E2:E273,$A8,'ROI por creator'!O2:O273) | F8: =SUMIF('ROI por creator'!E2:E273,$A8,'ROI por creator'!Q2:Q273) | G8: =SUMIF('ROI por creator'!E2:E273,$A8,'ROI por creator'!R2:R273) | H8: =SUMIF('ROI por creator'!E2:E273,$A8,'ROI por creator'!T2:T273) | I8: =IF(E8>0,F8/E8,0) | J8: =IF(E8>0,H8/E8,0)
A9: 2026-01 | B9: =COUNTIF('ROI por creator'!E2:E273,$A9) | C9: =SUMIF('ROI por creator'!E2:E273,$A9,'ROI por creator'!I2:I273) | D9: =SUMIF('ROI por creator'!E2:E273,$A9,'ROI por creator'!J2:J273) | E9: =SUMIF('ROI por creator'!E2:E273,$A9,'ROI por creator'!O2:O273) | F9: =SUMIF('ROI por creator'!E2:E273,$A9,'ROI por creator'!Q2:Q273) | G9: =SUMIF('ROI por creator'!E2:E273,$A9,'ROI por creator'!R2:R273) | H9: =SUMIF('ROI por creator'!E2:E273,$A9,'ROI por creator'!T2:T273) | I9: =IF(E9>0,F9/E9,0) | J9: =IF(E9>0,H9/E9,0)
A10: 2026-02 | B10: =COUNTIF('ROI por creator'!E2:E273,$A10) | C10: =SUMIF('ROI por creator'!E2:E273,$A10,'ROI por creator'!I2:I273) | D10: =SUMIF('ROI por creator'!E2:E273,$A10,'ROI por creator'!J2:J273) | E10: =SUMIF('ROI por creator'!E2:E273,$A10,'ROI por creator'!O2:O273) | F10: =SUMIF('ROI por creator'!E2:E273,$A10,'ROI por creator'!Q2:Q273) | G10: =SUMIF('ROI por creator'!E2:E273,$A10,'ROI por creator'!R2:R273) | H10: =SUMIF('ROI por creator'!E2:E273,$A10,'ROI por creator'!T2:T273) | I10: =IF(E10>0,F10/E10,0) | J10: =IF(E10>0,H10/E10,0)
A11: 2026-03 | B11: =COUNTIF('ROI por creator'!E2:E273,$A11) | C11: =SUMIF('ROI por creator'!E2:E273,$A11,'ROI por creator'!I2:I273) | D11: =SUMIF('ROI por creator'!E2:E273,$A11,'ROI por creator'!J2:J273) | E11: =SUMIF('ROI por creator'!E2:E273,$A11,'ROI por creator'!O2:O273) | F11: =SUMIF('ROI por creator'!E2:E273,$A11,'ROI por creator'!Q2:Q273) | G11: =SUMIF('ROI por creator'!E2:E273,$A11,'ROI por creator'!R2:R273) | H11: =SUMIF('ROI por creator'!E2:E273,$A11,'ROI por creator'!T2:T273) | I11: =IF(E11>0,F11/E11,0) | J11: =IF(E11>0,H11/E11,0)
A12: 2026-04 | B12: =COUNTIF('ROI por creator'!E2:E273,$A12) | C12: =SUMIF('ROI por creator'!E2:E273,$A12,'ROI por creator'!I2:I273) | D12: =SUMIF('ROI por creator'!E2:E273,$A12,'ROI por creator'!J2:J273) | E12: =SUMIF('ROI por creator'!E2:E273,$A12,'ROI por creator'!O2:O273) | F12: =SUMIF('ROI por creator'!E2:E273,$A12,'ROI por creator'!Q2:Q273) | G12: =SUMIF('ROI por creator'!E2:E273,$A12,'ROI por creator'!R2:R273) | H12: =SUMIF('ROI por creator'!E2:E273,$A12,'ROI por creator'!T2:T273) | I12: =IF(E12>0,F12/E12,0) | J12: =IF(E12>0,H12/E12,0)
A13: 2026-05 | B13: =COUNTIF('ROI por creator'!E2:E273,$A13) | C13: =SUMIF('ROI por creator'!E2:E273,$A13,'ROI por creator'!I2:I273) | D13: =SUMIF('ROI por creator'!E2:E273,$A13,'ROI por creator'!J2:J273) | E13: =SUMIF('ROI por creator'!E2:E273,$A13,'ROI por creator'!O2:O273) | F13: =SUMIF('ROI por creator'!E2:E273,$A13,'ROI por creator'!Q2:Q273) | G13: =SUMIF('ROI por creator'!E2:E273,$A13,'ROI por creator'!R2:R273) | H13: =SUMIF('ROI por creator'!E2:E273,$A13,'ROI por creator'!T2:T273) | I13: =IF(E13>0,F13/E13,0) | J13: =IF(E13>0,H13/E13,0)
A14: 2026-06 | B14: =COUNTIF('ROI por creator'!E2:E273,$A14) | C14: =SUMIF('ROI por creator'!E2:E273,$A14,'ROI por creator'!I2:I273) | D14: =SUMIF('ROI por creator'!E2:E273,$A14,'ROI por creator'!J2:J273) | E14: =SUMIF('ROI por creator'!E2:E273,$A14,'ROI por creator'!O2:O273) | F14: =SUMIF('ROI por creator'!E2:E273,$A14,'ROI por creator'!Q2:Q273) | G14: =SUMIF('ROI por creator'!E2:E273,$A14,'ROI por creator'!R2:R273) | H14: =SUMIF('ROI por creator'!E2:E273,$A14,'ROI por creator'!T2:T273) | I14: =IF(E14>0,F14/E14,0) | J14: =IF(E14>0,H14/E14,0)
A15: 2026-07 | B15: =COUNTIF('ROI por creator'!E2:E273,$A15) | C15: =SUMIF('ROI por creator'!E2:E273,$A15,'ROI por creator'!I2:I273) | D15: =SUMIF('ROI por creator'!E2:E273,$A15,'ROI por creator'!J2:J273) | E15: =SUMIF('ROI por creator'!E2:E273,$A15,'ROI por creator'!O2:O273) | F15: =SUMIF('ROI por creator'!E2:E273,$A15,'ROI por creator'!Q2:Q273) | G15: =SUMIF('ROI por creator'!E2:E273,$A15,'ROI por creator'!R2:R273) | H15: =SUMIF('ROI por creator'!E2:E273,$A15,'ROI por creator'!T2:T273) | I15: =IF(E15>0,F15/E15,0) | J15: =IF(E15>0,H15/E15,0)
A16: — | B16: =COUNTIF('ROI por creator'!E2:E273,$A16) | C16: =SUMIF('ROI por creator'!E2:E273,$A16,'ROI por creator'!I2:I273) | D16: =SUMIF('ROI por creator'!E2:E273,$A16,'ROI por creator'!J2:J273) | E16: =SUMIF('ROI por creator'!E2:E273,$A16,'ROI por creator'!O2:O273) | F16: =SUMIF('ROI por creator'!E2:E273,$A16,'ROI por creator'!Q2:Q273) | G16: =SUMIF('ROI por creator'!E2:E273,$A16,'ROI por creator'!R2:R273) | H16: =SUMIF('ROI por creator'!E2:E273,$A16,'ROI por creator'!T2:T273) | I16: =IF(E16>0,F16/E16,0) | J16: =IF(E16>0,H16/E16,0)
A17: TOTAL | B17: =SUM(B2:B16) | C17: =SUM(C2:C16) | D17: =SUM(D2:D16) | E17: =SUM(E2:E16) | F17: =SUM(F2:F16) | G17: =SUM(G2:G16) | H17: =SUM(H2:H16) | I17: =IF(E17>0,F17/E17,0) | J17: =IF(E17>0,H17/E17,0)

Sheet Metodologia
B1: Metodologia & fontes
B3: Fonte das peças (100% API TikTok Shop)
B4: • Endpoint: POST /affiliate_seller/202409/sample_applications/search — pedidos de free sample do TikTok.
B5: • 1 linha por creator × SKU pedido. Persistido em warehouse/raw_sample_applications.csv. total_count=337.
B6: • 'Peça enviada' = status em COMPLETED, SHIPPED ou CONTENT_PENDING (peça de fato despachada).
B7: • Status excluídos: *_CANCELLED (cancelada antes do envio) e AWAITING_SHIPMENT (aprovada, ainda não despachada).
B8: • 'Peças enviadas' por creator = nº de pedidos de amostra com status enviado. É o que vira CUSTO.
B9: • '1º/Último convite' = create_time do pedido de amostra (via API de Order, GET /order/202309/orders). '—' = pedido fora da retenção da API.
B10: • 'Status envio': Enviado (≥1 peça despachada) vs Nada enviado (pediu mas tudo cancelado/pendente). Use o AUTOFILTRO do cabeçalho; o TOTAL (SUBTOTAL) responde ao filtro.
B12: Comissão
B13: • 'Comissão %' = FAIXA acordada (8% ou 12%), consolidada das taxas reais da API (8/9/10% → 8%; 12% → 12%).
B14: • 'Comissão paga (R$)' = comissão REAL das vendas (raw_creator_product), não taxa × GMV.
... B31: • Cada pedido de amostra = 1 unidade de 1 SKU (a API não expõe múltiplas unidades por pedido).
